<annotation>
    <folder>P&amp;IDs</folder>
    <filename>Round XX-nnnn-nn 10.png</filename>
    <size>
        <width>821</width>
        <height>649</height>
        <depth>3</depth>
    </size>
    <object>
        <name>Instrument</name>
        <pose>Unspecified</pose>
        <truncated>0</truncated>
        <occluded>0</occluded>
        <difficult>0</difficult>
        <bndbox>
            <xmin>84.897682</xmin>
            <ymin>457.295837</ymin>
            <xmax>119.855057</xmax>
            <ymax>494.238831</ymax>
        </bndbox>
    </object>
    <object>
        <name>Instrument</name>
        <pose>Unspecified</pose>
        <truncated>0</truncated>
        <occluded>0</occluded>
        <difficult>0</difficult>
        <bndbox>
            <xmin>116.858711</xmin>
            <ymin>404.377502</ymin>
            <xmax>154.812424</xmax>
            <ymax>439.323578</ymax>
        </bndbox>
    </object>
    <object>
        <name>Instrument</name>
        <pose>Unspecified</pose>
        <truncated>0</truncated>
        <occluded>0</occluded>
        <difficult>0</difficult>
        <bndbox>
            <xmin>38.953716</xmin>
            <ymin>290.553162</ymin>
            <xmax>78.904999</xmax>
            <ymax>325.499237</ymax>
        </bndbox>
    </object>
    <object>
        <name>Instrument</name>
        <pose>Unspecified</pose>
        <truncated>0</truncated>
        <occluded>0</occluded>
        <difficult>0</difficult>
        <bndbox>
            <xmin>437.467712</xmin>
            <ymin>325.499237</ymin>
            <xmax>472.425110</xmax>
            <ymax>360.445312</ymax>
        </bndbox>
    </object>
    <object>
        <name>Instrument</name>
        <pose>Unspecified</pose>
        <truncated>0</truncated>
        <occluded>0</occluded>
        <difficult>0</difficult>
        <bndbox>
            <xmin>445.457977</xmin>
            <ymin>15.976885</ymin>
            <xmax>481.414093</xmax>
            <ymax>55.915253</ymax>
        </bndbox>
    </object>
    <object>
        <name>Instrument</name>
        <pose>Unspecified</pose>
        <truncated>0</truncated>
        <occluded>0</occluded>
        <difficult>0</difficult>
        <bndbox>
            <xmin>294.641907</xmin>
            <ymin>39.939907</ymin>
            <xmax>331.596832</xmax>
            <ymax>76.882889</ymax>
        </bndbox>
    </object>
    <object>
        <name>Instrument</name>
        <pose>Unspecified</pose>
        <truncated>0</truncated>
        <occluded>0</occluded>
        <difficult>0</difficult>
        <bndbox>
            <xmin>237.711334</xmin>
            <ymin>38.941444</ymin>
            <xmax>272.668701</xmax>
            <ymax>77.881348</ymax>
        </bndbox>
    </object>
    <object>
        <name>Instrument</name>
        <pose>Unspecified</pose>
        <truncated>0</truncated>
        <occluded>0</occluded>
        <difficult>0</difficult>
        <bndbox>
            <xmin>163.801453</xmin>
            <ymin>69.893677</ymin>
            <xmax>200.756393</xmax>
            <ymax>106.836655</ymax>
        </bndbox>
    </object>
    <object>
        <name>Instrument-square</name>
        <pose>Unspecified</pose>
        <truncated>0</truncated>
        <occluded>0</occluded>
        <difficult>0</difficult>
        <bndbox>
            <xmin>113.862366</xmin>
            <ymin>343.471497</ymin>
            <xmax>165.799026</xmax>
            <ymax>380.414490</ymax>
        </bndbox>
    </object>
    <object>
        <name>Instrument-square</name>
        <pose>Unspecified</pose>
        <truncated>0</truncated>
        <occluded>0</occluded>
        <difficult>0</difficult>
        <bndbox>
            <xmin>94.885506</xmin>
            <ymin>289.554688</ymin>
            <xmax>147.820953</xmax>
            <ymax>328.494598</ymax>
        </bndbox>
    </object>
    <object>
        <name>Instrument-square</name>
        <pose>Unspecified</pose>
        <truncated>0</truncated>
        <occluded>0</occluded>
        <difficult>0</difficult>
        <bndbox>
            <xmin>364.556641</xmin>
            <ymin>323.502319</ymin>
            <xmax>419.489624</xmax>
            <ymax>362.442200</ymax>
        </bndbox>
    </object>
    <object>
        <name>Instrument-square</name>
        <pose>Unspecified</pose>
        <truncated>0</truncated>
        <occluded>0</occluded>
        <difficult>0</difficult>
        <bndbox>
            <xmin>495.397095</xmin>
            <ymin>15.976885</ymin>
            <xmax>549.331299</xmax>
            <ymax>54.916794</ymax>
        </bndbox>
    </object>
    <object>
        <name>Instrument-square</name>
        <pose>Unspecified</pose>
        <truncated>0</truncated>
        <occluded>0</occluded>
        <difficult>0</difficult>
        <bndbox>
            <xmin>354.568817</xmin>
            <ymin>39.939907</ymin>
            <xmax>409.501831</xmax>
            <ymax>78.879814</ymax>
        </bndbox>
    </object>
    <object>
        <name>Instrument-square</name>
        <pose>Unspecified</pose>
        <truncated>0</truncated>
        <occluded>0</occluded>
        <difficult>0</difficult>
        <bndbox>
            <xmin>157.808777</xmin>
            <ymin>15.976885</ymin>
            <xmax>210.744202</xmax>
            <ymax>53.918327</ymax>
        </bndbox>
    </object>
</annotation>