<annotation>
    <folder>P&amp;IDs</folder>
    <filename>Round nn-XX-nnnn 92.png</filename>
    <size>
        <width>847</width>
        <height>707</height>
        <depth>3</depth>
    </size>
    <object>
        <name>Instrument</name>
        <pose>Unspecified</pose>
        <truncated>0</truncated>
        <occluded>0</occluded>
        <difficult>0</difficult>
        <bndbox>
            <xmin>575.321106</xmin>
            <ymin>283.599701</ymin>
            <xmax>614.275085</xmax>
            <ymax>327.537476</ymax>
        </bndbox>
    </object>
    <object>
        <name>Instrument</name>
        <pose>Unspecified</pose>
        <truncated>0</truncated>
        <occluded>0</occluded>
        <difficult>0</difficult>
        <bndbox>
            <xmin>713.158203</xmin>
            <ymin>620.123047</ymin>
            <xmax>758.105103</xmax>
            <ymax>662.063660</ymax>
        </bndbox>
    </object>
    <object>
        <name>Instrument</name>
        <pose>Unspecified</pose>
        <truncated>0</truncated>
        <occluded>0</occluded>
        <difficult>0</difficult>
        <bndbox>
            <xmin>714.157043</xmin>
            <ymin>438.380463</ymin>
            <xmax>754.109863</xmax>
            <ymax>475.328125</ymax>
        </bndbox>
    </object>
    <object>
        <name>Instrument</name>
        <pose>Unspecified</pose>
        <truncated>0</truncated>
        <occluded>0</occluded>
        <difficult>0</difficult>
        <bndbox>
            <xmin>118.860687</xmin>
            <ymin>495.299835</ymin>
            <xmax>157.814636</xmax>
            <ymax>533.246094</ymax>
        </bndbox>
    </object>
    <object>
        <name>Instrument</name>
        <pose>Unspecified</pose>
        <truncated>0</truncated>
        <occluded>0</occluded>
        <difficult>0</difficult>
        <bndbox>
            <xmin>170.799301</xmin>
            <ymin>206.708633</ymin>
            <xmax>221.739090</xmax>
            <ymax>249.647797</ymax>
        </bndbox>
    </object>
    <object>
        <name>Instrument</name>
        <pose>Unspecified</pose>
        <truncated>0</truncated>
        <occluded>0</occluded>
        <difficult>0</difficult>
        <bndbox>
            <xmin>289.658813</xmin>
            <ymin>112.841591</ymin>
            <xmax>330.610382</xmax>
            <ymax>150.787811</ymax>
        </bndbox>
    </object>
    <object>
        <name>Instrument-square</name>
        <pose>Unspecified</pose>
        <truncated>0</truncated>
        <occluded>0</occluded>
        <difficult>0</difficult>
        <bndbox>
            <xmin>127.850060</xmin>
            <ymin>169.760941</ymin>
            <xmax>176.792206</xmax>
            <ymax>213.698730</ymax>
        </bndbox>
    </object>
    <object>
        <name>Instrument-square</name>
        <pose>Unspecified</pose>
        <truncated>0</truncated>
        <occluded>0</occluded>
        <difficult>0</difficult>
        <bndbox>
            <xmin>633.252625</xmin>
            <ymin>286.595490</ymin>
            <xmax>678.199524</xmax>
            <ymax>326.538910</ymax>
        </bndbox>
    </object>
    <object>
        <name>Instrument-square</name>
        <pose>Unspecified</pose>
        <truncated>0</truncated>
        <occluded>0</occluded>
        <difficult>0</difficult>
        <bndbox>
            <xmin>361.573792</xmin>
            <ymin>108.847237</ymin>
            <xmax>412.513550</xmax>
            <ymax>152.785019</ymax>
        </bndbox>
    </object>
</annotation>